README.md
setup.cfg
setup.py
dyu_accounting/__init__.py
dyu_accounting.egg-info/PKG-INFO
dyu_accounting.egg-info/SOURCES.txt
dyu_accounting.egg-info/dependency_links.txt
dyu_accounting.egg-info/entry_points.txt
dyu_accounting.egg-info/requires.txt
dyu_accounting.egg-info/top_level.txt
dyu_accounting/Utilities/__init__.py
dyu_accounting/balance_sheet/__init__.py
dyu_accounting/depreciation/__init__.py
dyu_accounting/exchange_gain/__init__.py
dyu_accounting/gst/__init__.py
dyu_accounting/journal/__init__.py
dyu_accounting/pnl/__init__.py
dyu_accounting/templates/GST.tpl
dyu_accounting/templates/PnL.tpl
dyu_accounting/templates/__init__.py
dyu_accounting/templates/balancesheet.tpl
dyu_accounting/templates/base.tpl
dyu_accounting/templates/depreciation.tpl
dyu_accounting/templates/index.tpl
dyu_accounting/templates/journal.tpl
test/test_shareCapital.py