Metadata-Version: 1.1
Name: dyu-accounting
Version: 0.1.0
Summary: A Package for 
Home-page: https://github.com/dyumnin/dyu_accounting
Author: Vijayvithal Jahagirdar
Author-email: support@dyumnin.com
License: GPL 2
Platform: UNKNOWN
Classifier: Development Status :: 1 - Planning
Classifier: Intended Audience :: Financial and Insurance Industry
Classifier: Topic :: Office/Business :: Financial :: Accounting
Classifier: License :: Free for non-commercial use
Classifier: License :: OSI Approved :: GNU General Public License (GPL)
Classifier: Operating System :: POSIX :: Linux
Classifier: Programming Language :: Python :: 3
